objdiff.py
objdiff-1.2.3.dist-info/DESCRIPTION.rst
objdiff-1.2.3.dist-info/METADATA
objdiff-1.2.3.dist-info/RECORD
objdiff-1.2.3.dist-info/WHEEL
objdiff-1.2.3.dist-info/metadata.json
objdiff-1.2.3.dist-info/top_level.txt
objdiff-1.2.3.dist-info/zip-safe
