Metadata-Version: 2.0
Name: objdiff
Version: 1.2.3
Summary: Returns a list of commands/delta to go from one tree of objects to another
Home-page: http://blitz.works/objdiff
Author: Da_Blitz
Author-email: code@pocketnix.org
License: MIT BSD
Download-URL: http://blitz.works/objdiff/archive/default.zip
Keywords: objects diff tree difflib patch diffrence
Platform: UNKNOWN
Classifier: Development Status :: 5 - Production/Stable
Classifier: Intended Audience :: Developers
Classifier: License :: OSI Approved :: BSD License
Classifier: Topic :: Software Development :: Libraries
Requires-Dist: distribute
